webpet/__init__.py
webpet/application.py
webpet-0.1.1.dist-info/LICENSE.txt
webpet-0.1.1.dist-info/METADATA
webpet-0.1.1.dist-info/WHEEL
webpet-0.1.1.dist-info/top_level.txt
webpet-0.1.1.dist-info/RECORD
