Metadata-Version: 2.1
Name: webpet
Version: 0.1.1
Summary: My simple async web framework
Home-page: https://github.com/momoru-kun/webpet
Author: Aleksandr Lenets (aka momoru_kun)
Author-email: wowgonit@gmail.com
License: MIT
Keywords: web,http,async,framework
Platform: UNKNOWN
Classifier: Environment :: Web Environment
Classifier: Development Status :: 3 - Alpha
Classifier: Intended Audience :: Developers
Classifier: Topic :: Internet :: WWW/HTTP
Classifier: Topic :: Internet :: WWW/HTTP :: WSGI
Classifier: Topic :: Internet :: WWW/HTTP :: Dynamic Content
Classifier: Topic :: Software Development :: Libraries :: Application Frameworks
Classifier: Topic :: Software Development :: Libraries :: Python Modules
Classifier: License :: OSI Approved :: MIT License
Classifier: Programming Language :: Python :: 3.7
Classifier: Programming Language :: Python :: 3.8
Classifier: Programming Language :: Python :: 3.9
License-File: LICENSE.txt
Requires-Dist: jinja2 (==3.0.2)
Requires-Dist: aiofiles (==0.7.0)
